README.txt
setup.py
pymarkoff/__init__.py
pymarkoff/__main__.py
pymarkoff.egg-info/PKG-INFO
pymarkoff.egg-info/SOURCES.txt
pymarkoff.egg-info/dependency_links.txt
pymarkoff.egg-info/top_level.txt
pymarkoff.egg-info/zip-safe